api_clone/__init__.py
api_clone/api_downloader.py
api_clone-0.0.2.dist-info/METADATA
api_clone-0.0.2.dist-info/WHEEL
api_clone-0.0.2.dist-info/licenses/LICENSE
api_clone-0.0.2.dist-info/RECORD
