Metadata-Version: 2.1
Name: api_clone
Version: 0.0.2
Summary: An script for saving json data and results locally on your machine 
Project-URL: Homepage, https://github.com/AnthonyAniobi/Api_Clone
Project-URL: Bug Tracker, https://github.com/AnthonyAniobi/Api_Clone/issues
Author-email: Anthony Aniobi <anthonyaniobi198@gmail.com>
License-File: LICENSE
Classifier: License :: OSI Approved :: MIT License
Classifier: Operating System :: OS Independent
Classifier: Programming Language :: Python :: 3
Requires-Python: >=3.7
Requires-Dist: pil
Requires-Dist: requests
